diamond/__init__.py
diamond/f.py
diamond_f-2.0.0.dist-info/LICENSE
diamond_f-2.0.0.dist-info/METADATA
diamond_f-2.0.0.dist-info/WHEEL
diamond_f-2.0.0.dist-info/top_level.txt
diamond_f-2.0.0.dist-info/RECORD
